[
  {
    "name": "Početna",
    "route": "/"
  },
  {
    "name": "Medijacija",
    "children": [
      {
        "name": "Šta je medijacija?",
        "route": "sta-je-medijacija"
      },
      {
        "name": "Zašto medijacija?",
        "route": "zasto-medijacija"
      },
      {
        "name": "Kada je moguća?",
        "route": "kada-je-moguca"
      },
      {
        "name": "Postupak",
        "route": "postupak"
      },
      {
        "name": "Onlajn medijacija",
        "route": "onlajn-medijacija"
      },
      {
        "name": "Tarifnik",
        "route": "tarifnik"
      }
    ]
  },
  {
    "name": "Edukacija",
    "children": [
      {
        "name": "Pravni okvir",
        "route": "pravni-okvir"
      },
      {
        "name": "Česta pitanja",
        "route": "cesta-pitanja"
      }
    ]
  },
  {
    "name": "Kontakt",
    "route": "kontakt"
  },
  {
    "name": "O nama",
    "route": "o-nama"
  },
  {
    "name": "English",
    "children": [
      {
        "name": "Mediation",
        "route": "mediation"
      },
      {
        "name": "Areas of mediation",
        "route": "areas-of-mediation"
      },
      {
        "name": "Faq",
        "route": "faq"
      }
    ]
  }
]